bittensor_cli/__init__.py
bittensor_cli/cli.py
bittensor_cli/doc_generation_helper.py
bittensor_cli/version.py
bittensor_cli/src/__init__.py
bittensor_cli/src/bittensor/__init__.py
bittensor_cli/src/bittensor/balances.py
bittensor_cli/src/bittensor/chain_data.py
bittensor_cli/src/bittensor/minigraph.py
bittensor_cli/src/bittensor/networking.py
bittensor_cli/src/bittensor/subtensor_interface.py
bittensor_cli/src/bittensor/utils.py
bittensor_cli/src/bittensor/extrinsics/__init__.py
bittensor_cli/src/bittensor/extrinsics/mev_shield.py
bittensor_cli/src/bittensor/extrinsics/registration.py
bittensor_cli/src/bittensor/extrinsics/root.py
bittensor_cli/src/bittensor/extrinsics/serving.py
bittensor_cli/src/bittensor/extrinsics/transfer.py
bittensor_cli/src/bittensor/templates/main-filters.j2
bittensor_cli/src/bittensor/templates/main-header.j2
bittensor_cli/src/bittensor/templates/neuron-details.j2
bittensor_cli/src/bittensor/templates/price-multi.j2
bittensor_cli/src/bittensor/templates/price-single.j2
bittensor_cli/src/bittensor/templates/subnet-details-header.j2
bittensor_cli/src/bittensor/templates/subnet-details.j2
bittensor_cli/src/bittensor/templates/subnet-metrics.j2
bittensor_cli/src/bittensor/templates/subnets-table.j2
bittensor_cli/src/bittensor/templates/table.j2
bittensor_cli/src/bittensor/templates/view.css
bittensor_cli/src/bittensor/templates/view.j2
bittensor_cli/src/bittensor/templates/view.js
bittensor_cli/src/commands/__init__.py
bittensor_cli/src/commands/proxy.py
bittensor_cli/src/commands/sudo.py
bittensor_cli/src/commands/view.py
bittensor_cli/src/commands/wallets.py
bittensor_cli/src/commands/weights.py
bittensor_cli/src/commands/axon/__init__.py
bittensor_cli/src/commands/axon/axon.py
bittensor_cli/src/commands/crowd/__init__.py
bittensor_cli/src/commands/crowd/contribute.py
bittensor_cli/src/commands/crowd/contributors.py
bittensor_cli/src/commands/crowd/create.py
bittensor_cli/src/commands/crowd/dissolve.py
bittensor_cli-9.18.0.dist-info/entry_points.txt
bittensor_cli-9.18.0.dist-info/WHEEL
bittensor_cli-9.18.0.dist-info/METADATA
bittensor_cli-9.18.0.dist-info/RECORD
