Metadata-Version: 2.4
Name: bittensor-cli
Version: 9.18.0
Summary: Bittensor CLI
Author: bittensor.com
Requires-Python: >=3.9
License-Expression: MIT
Classifier: Development Status :: 5 - Production/Stable
Classifier: Intended Audience :: End Users/Desktop
Classifier: Programming Language :: Python :: 3 :: Only
Classifier: Programming Language :: Python :: 3.9
Classifier: Programming Language :: Python :: 3.10
Classifier: Programming Language :: Python :: 3.11
Classifier: Programming Language :: Python :: 3.12
Classifier: Programming Language :: Python :: 3.13
Classifier: Programming Language :: Python :: 3.14
Classifier: Topic :: Scientific/Engineering
Classifier: Topic :: Scientific/Engineering :: Mathematics
Classifier: Topic :: Scientific/Engineering :: Artificial Intelligence
Classifier: Topic :: Utilities
Requires-Dist: wheel
Requires-Dist: async-substrate-interface>=1.6.0
Requires-Dist: aiohttp~=3.13
Requires-Dist: backoff~=2.2.1
Requires-Dist: bittensor-drand>=1.2.0
Requires-Dist: GitPython>=3.0.0
Requires-Dist: netaddr~=1.3.0
Requires-Dist: numpy>=2.0.1,<3.0.0
Requires-Dist: Jinja2
Requires-Dist: pycryptodome>=3.0.0,<4.0.0
Requires-Dist: PyYAML~=6.0
Requires-Dist: rich>=13.7,<15.0
Requires-Dist: scalecodec==1.2.12
Requires-Dist: typer>=0.16
Requires-Dist: bittensor-wallet>=4.0.0
Requires-Dist: packaging
Requires-Dist: plotille>=5.0.0
Requires-Dist: plotly>=6.0.0
Requires-Dist: torch>=1.13.1,<3.0 ; extra == "cuda"
Project-URL: Repository, https://github.com/opentensor/btcli
Project-URL: homepage, https://github.com/opentensor/btcli
Provides-Extra: cuda
